FireBased/__init__.py
FireBased/client/__init__.py
FireBased/client/client.py
FireBased/client/schemas.py
FireBased/client/settings.py
FireBased/client/proto/__init__.py
FireBased/ext/__init__.py
FireBased/ext/synthetic_data.py
FireBased/ext/synthetics.py
firebased-0.0.3.post3.dist-info/LICENSE
firebased-0.0.3.post3.dist-info/METADATA
firebased-0.0.3.post3.dist-info/WHEEL
firebased-0.0.3.post3.dist-info/top_level.txt
firebased-0.0.3.post3.dist-info/RECORD
