Metadata-Version: 2.2
Name: FireBased
Version: 0.0.3.post3
Summary: Firebase token generation
Home-page: https://github.com/isaackogan/FireBased
Author: Tricorder
Author-email: tricorder@isaackogan.com
License: MIT
Keywords: Firebase,Reverse Engineering,python3,api,unofficial
Classifier: Development Status :: 4 - Beta
Classifier: Intended Audience :: Developers
Classifier: Topic :: Software Development :: Build Tools
Classifier: License :: OSI Approved :: MIT License
Classifier: Natural Language :: English
Classifier: Programming Language :: Python :: 3.12
Classifier: Framework :: Pydantic :: 2
License-File: LICENSE
Requires-Dist: httpx
Requires-Dist: betterproto==2.0.0b7
Requires-Dist: pydantic>=2.0.0
Dynamic: author
Dynamic: author-email
Dynamic: classifier
Dynamic: description
Dynamic: description-content-type
Dynamic: home-page
Dynamic: keywords
Dynamic: license
Dynamic: requires-dist
Dynamic: summary
